indieweb/__init__.py
indieweb/admin.py
indieweb/h_card.py
indieweb/handlers.py
indieweb/handlers_example.py
indieweb/interfaces.py
indieweb/management/__init__.py
indieweb/management/commands/__init__.py
indieweb/management/commands/send_webmentions.py
indieweb/migrations/0001_initial.py
indieweb/migrations/0002_alter_auth_state.py
indieweb/migrations/0002_auto_20190512_0612.py
indieweb/migrations/0003_auto_20190518_0207.py
indieweb/migrations/0004_alter_auth_id_alter_token_id.py
indieweb/migrations/0005_alter_auth_created_alter_auth_modified_and_more.py
indieweb/migrations/0006_merge_20250628_1513.py
indieweb/migrations/0007_alter_token_me.py
indieweb/migrations/0008_webmention.py
indieweb/migrations/0009_profile.py
indieweb/migrations/__init__.py
indieweb/models.py
indieweb/processors.py
indieweb/senders.py
indieweb/static/css/indieweb.css
indieweb/static/css/webmentions.css
indieweb/static/img/.gitignore
indieweb/static/js/indieweb.js
indieweb/templates/indieweb/base.html
indieweb/templates/indieweb/consent.html
indieweb/templates/indieweb/h-card.html
indieweb/templates/indieweb/webmention_types/like.html
indieweb/templates/indieweb/webmention_types/mention.html
indieweb/templates/indieweb/webmention_types/reply.html
indieweb/templates/indieweb/webmention_types/repost.html
indieweb/templates/indieweb/webmentions.html
indieweb/templates/indieweb/webmentions_example.html
indieweb/templatetags/__init__.py
indieweb/templatetags/indieweb_tags.py
indieweb/templatetags/webmention_tags.py
indieweb/urls.py
indieweb/views.py
django_indieweb-0.5.2.dist-info/WHEEL
django_indieweb-0.5.2.dist-info/METADATA
django_indieweb-0.5.2.dist-info/RECORD
