Metadata-Version: 2.3
Name: django-indieweb
Version: 0.5.2
Summary: includes indieauth, micropub, and webmention endpoints
Keywords: indieweb,indieauth,micropub,webmention,django
Author: Jochen Wersdörfer
Author-email: Jochen Wersdörfer <jochen-indieweb@wersdoerfer.de>
Classifier: Programming Language :: Python :: 3
Classifier: Programming Language :: Python
Classifier: Framework :: Django
Classifier: License :: OSI Approved :: BSD License
Classifier: Topic :: Internet
Classifier: Intended Audience :: Developers
Classifier: Operating System :: OS Independent
Classifier: Topic :: Internet :: WWW/HTTP
Classifier: Topic :: Internet :: WWW/HTTP :: Dynamic Content
Classifier: Development Status :: 3 - Alpha
Classifier: Environment :: Web Environment
Classifier: Programming Language :: Python :: 3 :: Only
Classifier: Programming Language :: Python :: 3.10
Classifier: Programming Language :: Python :: 3.11
Classifier: Programming Language :: Python :: 3.12
Classifier: Programming Language :: Python :: 3.13
Requires-Dist: django
Requires-Dist: mf2py
Requires-Dist: beautifulsoup4
Requires-Dist: httpx
Requires-Python: >=3.10
Project-URL: Documentation, https://django-indieweb.readthedocs.io/en/latest/
Project-URL: Source, https://github.com/ephes/django-indieweb
